gen/.gitkeep
gen/__init__.py
gen/collections_pb2.py
gen/collections_pb2.pyi
gen/collections_pb2_grpc.py
gen/collections_service_pb2.py
gen/collections_service_pb2.pyi
gen/collections_service_pb2_grpc.py
gen/common_pb2.py
gen/common_pb2.pyi
gen/common_pb2_grpc.py
gen/embeds_pb2.py
gen/embeds_pb2.pyi
gen/embeds_pb2_grpc.py
gen/embeds_service_pb2.py
gen/embeds_service_pb2.pyi
gen/embeds_service_pb2_grpc.py
gen/search_pb2.py
gen/search_pb2.pyi
gen/search_pb2_grpc.py
gen/search_service_pb2.py
gen/search_service_pb2.pyi
gen/search_service_pb2_grpc.py
pulsejet_client/__init__.py
pulsejet_client/async_client.py
pulsejet_client/async_pj_base.py
pulsejet_client/async_pj_remote.py
pulsejet_client/client.py
pulsejet_client/cluster_client.py
pulsejet_client/connections.py
pulsejet_client/grpc_multi_inserter.py
pulsejet_client/parallel_processor.py
pulsejet_client/pj_base.py
pulsejet_client/pj_remote.py
pulsejet_client/types.py
pulsejet_client-0.1.9.dist-info/METADATA
pulsejet_client-0.1.9.dist-info/WHEEL
pulsejet_client-0.1.9.dist-info/RECORD
